README.md
requirements.txt
setup.py
./sgx/__init__.py
./sgx/archive.py
./sgx/base.py
./sgx/species.py
./sgx/algorithms/__init__.py
./sgx/algorithms/simple.py
./sgx/allele/__init__.py
./sgx/allele/base.py
./sgx/allele/boolean.py
./sgx/allele/categorical.py
./sgx/fitness/__init__.py
./sgx/fitness/base.py
./sgx/fitness/function.py
./sgx/fitness/multi_objective.py
./sgx/fitness/simple.py
./sgx/t/__init__.py
./sgx/utils/__init__.py
./sgx/utils/cpu_time.py
./sgx/utils/jupyter_support.py
./sgx/utils/logging.py
./sgx/utils/random.py
./tests/__init__.py
./tests/test_categorical.py
./tests/test_random.py
./tests/test_sgx.py
sgx/__init__.py
sgx/archive.py
sgx/base.py
sgx/species.py
sgx.egg-info/PKG-INFO
sgx.egg-info/SOURCES.txt
sgx.egg-info/dependency_links.txt
sgx.egg-info/requires.txt
sgx.egg-info/top_level.txt
sgx/algorithms/__init__.py
sgx/algorithms/simple.py
sgx/allele/__init__.py
sgx/allele/base.py
sgx/allele/boolean.py
sgx/allele/categorical.py
sgx/fitness/__init__.py
sgx/fitness/base.py
sgx/fitness/function.py
sgx/fitness/multi_objective.py
sgx/fitness/simple.py
sgx/t/__init__.py
sgx/utils/__init__.py
sgx/utils/cpu_time.py
sgx/utils/jupyter_support.py
sgx/utils/logging.py
sgx/utils/random.py
tests/__init__.py
tests/test_categorical.py
tests/test_random.py
tests/test_sgx.py