Metadata-Version: 2.1
Name: sgx
Version: 0.2.dev4
Summary: A population-less EA loosely inspired by a cool interpretation of the Darwinian theory
Home-page: https://github.com/squillero/sgx
Author: Giovanni Squillero
Author-email: squillero@polito.it
License: EUPL-1.2
Project-URL: Bug Tracker, https://github.com/squillero/sgx/issues
Project-URL: Source Code, https://github.com/squillero/sgx
Keywords: optimization evolutionary-algorithm computational-intelligence
Platform: UNKNOWN
Classifier: Programming Language :: Python :: 3
Classifier: Operating System :: OS Independent
Classifier: Development Status :: 2 - Pre-Alpha
Classifier: Intended Audience :: Science/Research
Classifier: Topic :: Scientific/Engineering :: Artificial Intelligence
Classifier: Topic :: Scientific/Engineering :: Mathematics
Classifier: License :: OSI Approved :: European Union Public Licence 1.2 (EUPL 1.2)
